terminaider/__init__.py
terminaider/agent.py
terminaider/ai_interface.py
terminaider/config.py
terminaider/main.py
terminaider/prompts.py
terminaider/run_chat.py
terminaider/utils.py
terminaider/themes/__init__.py
terminaider/themes/themes.py
terminaider-0.1.3.dist-info/LICENSE
terminaider-0.1.3.dist-info/METADATA
terminaider-0.1.3.dist-info/WHEEL
terminaider-0.1.3.dist-info/entry_points.txt
terminaider-0.1.3.dist-info/top_level.txt
terminaider-0.1.3.dist-info/RECORD
