Metadata-Version: 2.1
Name: terminaider
Version: 0.1.3
Summary: AI assistant for your terminal
Author-email: Daniel Ratmiroff <danielratmiroff@pm.me>
License:                                  Apache License
Project-URL: Homepage, https://github.com/Danielratmiroff/terminaider
Project-URL: Source, https://github.com/Danielratmiroff/terminaider
Project-URL: Bug Tracker, https://github.com/Danielratmiroff/terminaider/issues
Project-URL: Documentation, https://github.com/Danielratmiroff/terminaider#readme
Keywords: terminal,ai,automation,cli
Classifier: Programming Language :: Python :: 3
Classifier: License :: OSI Approved :: MIT License
Classifier: Operating System :: OS Independent
License-File: LICENSE
Requires-Dist: aiohappyeyeballs==2.4.3
Requires-Dist: aiohttp==3.10.10
Requires-Dist: aiosignal==1.3.1
Requires-Dist: annotated-types==0.7.0
Requires-Dist: anyio==4.6.2.post1
Requires-Dist: appdirs==1.4.4
Requires-Dist: attrs==24.2.0
Requires-Dist: build==1.2.2.post1
Requires-Dist: certifi==2024.8.30
Requires-Dist: cffi==1.17.1
Requires-Dist: charset-normalizer==3.4.0
Requires-Dist: click==8.1.7
Requires-Dist: colorama==0.4.6
Requires-Dist: cryptography==43.0.3
Requires-Dist: distro==1.9.0
Requires-Dist: docutils==0.21.2
Requires-Dist: fastapi==0.115.4
Requires-Dist: filelock==3.16.1
Requires-Dist: frozenlist==1.5.0
Requires-Dist: fsspec==2024.10.0
Requires-Dist: gitdb==4.0.11
Requires-Dist: GitPython==3.1.43
Requires-Dist: greenlet==3.1.1
Requires-Dist: gritql==0.1.5
Requires-Dist: groq==0.11.0
Requires-Dist: h11==0.14.0
Requires-Dist: httpcore==1.0.6
Requires-Dist: httpx==0.27.2
Requires-Dist: httpx-sse==0.4.0
Requires-Dist: huggingface-hub==0.26.2
Requires-Dist: idna==3.10
Requires-Dist: importlib_metadata==8.5.0
Requires-Dist: jaraco.classes==3.4.0
Requires-Dist: jaraco.context==6.0.1
Requires-Dist: jaraco.functools==4.1.0
Requires-Dist: jeepney==0.8.0
Requires-Dist: Jinja2==3.1.4
Requires-Dist: jiter==0.7.0
Requires-Dist: joblib==1.4.2
Requires-Dist: jsonpatch==1.33
Requires-Dist: jsonpointer==3.0.0
Requires-Dist: keyring==25.5.0
Requires-Dist: langchain==0.3.7
Requires-Dist: langchain-cli==0.0.31
Requires-Dist: langchain-core==0.3.15
Requires-Dist: langchain-groq==0.2.1
Requires-Dist: langchain-huggingface==0.1.2
Requires-Dist: langchain-openai==0.2.6
Requires-Dist: langchain-text-splitters==0.3.2
Requires-Dist: langgraph==0.2.45
Requires-Dist: langgraph-checkpoint==2.0.2
Requires-Dist: langgraph-sdk==0.1.35
Requires-Dist: langserve==0.3.0
Requires-Dist: langsmith==0.1.142
Requires-Dist: Markdown==3.7
Requires-Dist: markdown-it-py==3.0.0
Requires-Dist: MarkupSafe==3.0.2
Requires-Dist: mdurl==0.1.2
Requires-Dist: more-itertools==10.5.0
Requires-Dist: MouseInfo==0.1.3
Requires-Dist: mpmath==1.3.0
Requires-Dist: msgpack==1.1.0
Requires-Dist: multidict==6.1.0
Requires-Dist: networkx==3.4.2
Requires-Dist: nh3==0.2.18
Requires-Dist: numpy
Requires-Dist: openai==1.54.3
Requires-Dist: orjson==3.10.11
Requires-Dist: packaging==24.2
Requires-Dist: pillow==11.0.0
Requires-Dist: pkginfo==1.10.0
Requires-Dist: propcache==0.2.0
Requires-Dist: pycparser==2.22
Requires-Dist: pydantic
Requires-Dist: pydantic_core
Requires-Dist: Pygments==2.18.0
Requires-Dist: pyperclip==1.9.0
Requires-Dist: pyproject_hooks==1.2.0
Requires-Dist: PyRect==0.2.0
Requires-Dist: PyScreeze==1.0.1
Requires-Dist: python3-xlib==0.15
Requires-Dist: PyYAML==6.0.2
Requires-Dist: readme_renderer==44.0
Requires-Dist: regex==2024.11.6
Requires-Dist: requests==2.32.3
Requires-Dist: requests-toolbelt==1.0.0
Requires-Dist: rfc3986==2.0.0
Requires-Dist: rich==13.9.4
Requires-Dist: safetensors==0.4.5
Requires-Dist: scikit-learn==1.5.2
Requires-Dist: scipy==1.14.1
Requires-Dist: SecretStorage==3.3.3
Requires-Dist: sentence-transformers==3.3.0
Requires-Dist: setuptools==75.5.0
Requires-Dist: shellingham==1.5.4
Requires-Dist: six==1.16.0
Requires-Dist: smmap==5.0.1
Requires-Dist: sniffio==1.3.1
Requires-Dist: SQLAlchemy==2.0.36
Requires-Dist: sse-starlette
Requires-Dist: starlette
Requires-Dist: sympy==1.13.1
Requires-Dist: tenacity==9.0.0
Requires-Dist: threadpoolctl==3.5.0
Requires-Dist: tiktoken==0.8.0
Requires-Dist: tokenizers==0.20.3
Requires-Dist: tomlkit
Requires-Dist: torch==2.5.1
Requires-Dist: tqdm==4.67.0
Requires-Dist: transformers==4.46.2
Requires-Dist: triton==3.1.0
Requires-Dist: typer
Requires-Dist: typing_extensions==4.12.2
Requires-Dist: urllib3==2.2.3
Requires-Dist: uvicorn
Requires-Dist: yarl==1.17.1
Requires-Dist: zipp==3.21.0
